pdiff/__init__.py
pdiff/__main__.py
pdiff/__version__.py
pdiff/argument_parser.py
pdiff/colors.py
pdiff/diff_formatter.py
pdiff/terminal_util.py
pdiff-1.1.4.dist-info/LICENSE.txt
pdiff-1.1.4.dist-info/METADATA
pdiff-1.1.4.dist-info/WHEEL
pdiff-1.1.4.dist-info/entry_points.txt
pdiff-1.1.4.dist-info/top_level.txt
pdiff-1.1.4.dist-info/RECORD
