Metadata-Version: 2.1
Name: pdiff
Version: 1.1.4
Summary: Pretty side-by-side diff
Home-page: https://github.com/nkouevda/pdiff
Author: Nikita Kouevda
Author-email: nkouevda@gmail.com
License: MIT
License-File: LICENSE.txt
Requires-Dist: colorama
